mdx_link2md/__init__.py
mdx_link2md/__main__.py
mdx_link2md/markdownlinks.py
mdx_link2md-0.0.2.dist-info/METADATA
mdx_link2md-0.0.2.dist-info/RECORD
mdx_link2md-0.0.2.dist-info/WHEEL
mdx_link2md-0.0.2.dist-info/top_level.txt
