Metadata-Version: 2.1
Name: mdx-link2md
Version: 0.0.2
Summary: A markdown link preprocessor for Python Markdown
Home-page: https://github.com/scyu16/mdx_link2md
Author: scyu16
Author-email: devmaily@yandex.com
License: MIT
Keywords: markdown,html
Platform: UNKNOWN
Classifier: Topic :: Text Processing :: Markup
Classifier: Topic :: Utilities
Classifier: Programming Language :: Python :: 2.7
Classifier: Programming Language :: Python :: 3.6
Classifier: Programming Language :: Python :: 3.7
Classifier: Programming Language :: Python :: Implementation :: PyPy
Classifier: License :: OSI Approved :: MIT License
Requires-Dist: markdown (>=2.6.11)
